celescope/__init__.py
celescope/celescope.py
celescope/atac/__init__.py
celescope/atac/analysis.py
celescope/atac/atac.py
celescope/atac/barcode.py
celescope/atac/gen_plot_data.R
celescope/atac/mkref.py
celescope/atac/multi_atac.py
celescope/atac/peak_count.R
celescope/atac/sample.py
celescope/atac/scatac_filter.py
celescope/atac/scatac_peakcount.py
celescope/data/GRCm38_chrom_len.txt
celescope/data/sgr-atac-rna-V2.txt
celescope/data/sgr-atac-rna-V3-replaceA.txt
celescope/data/sgr-atac-rna-V3.txt
celescope/data/chemistry/737K-august-2016.txt
celescope/data/chemistry/atac1/857K-2023.txt
celescope/data/chemistry/atac1/bclist
celescope/data/chemistry/atac1/linker
celescope/data/chemistry/atac2/884K-2024.txt
celescope/data/chemistry/atac2/bclist
celescope/data/chemistry/atac2/linker
celescope/data/chemistry/atac3/884K-2025.txt
celescope/data/chemistry/atac3/bclist
celescope/data/chemistry/atac3/linker
celescope/templates/css/bootstrap.min.css
celescope/templates/css/buttons.dataTables.min.css
celescope/templates/css/dataTables.jqueryui.min.css
celescope/templates/css/jquery-ui-git.css
celescope/templates/css/jquery-ui.css
celescope/templates/css/jquery.dataTables.css
celescope/templates/css/fontello-323401c3/config.json
celescope/templates/css/fontello-323401c3/css/animation.css
celescope/templates/css/fontello-323401c3/css/fontello-codes.css
celescope/templates/css/fontello-323401c3/css/fontello-embedded.css
celescope/templates/css/fontello-323401c3/css/fontello-ie7-codes.css
celescope/templates/css/fontello-323401c3/css/fontello-ie7.css
celescope/templates/css/fontello-323401c3/css/fontello.css
celescope/templates/css/fontello-323401c3/font/fontello.eot
celescope/templates/css/fontello-323401c3/font/fontello.svg
celescope/templates/css/fontello-323401c3/font/fontello.ttf
celescope/templates/css/fontello-323401c3/font/fontello.woff
celescope/templates/css/fontello-323401c3/font/fontello.woff2
celescope/templates/html/atac/analysis.html
celescope_atac-1.8.1.dist-info/licenses/LICENSE
celescope_atac-1.8.1.dist-info/METADATA
celescope_atac-1.8.1.dist-info/WHEEL
celescope_atac-1.8.1.dist-info/entry_points.txt
celescope_atac-1.8.1.dist-info/top_level.txt
celescope_atac-1.8.1.dist-info/RECORD
