Metadata-Version: 2.4
Name: celescope_atac
Version: 1.8.1
Summary: Single Cell ATAC-Seq Analysis Pipelines
Home-page: https://github.com/singleron-RD/CeleScope_ATAC
Author: chenjunjie
Author-email: chenjunjie@singleronbio.com
Classifier: Programming Language :: Python :: 3
Classifier: License :: OSI Approved :: MIT License
Classifier: Operating System :: OS Independent
Requires-Python: >=3.6
License-File: LICENSE
Requires-Dist: xopen>=0.5.0
Requires-Dist: plotly==5.24.1
Requires-Dist: leidenalg==0.10.2
Requires-Dist: scanpy==1.10.3
Requires-Dist: h5py==3.13.0
Requires-Dist: scipy==1.13.1
Requires-Dist: tables==3.8.0
Requires-Dist: pandas==2.1.1
Requires-Dist: pysam>=0.18.0
Requires-Dist: jinja2>=2.10
Dynamic: author
Dynamic: author-email
Dynamic: classifier
Dynamic: description
Dynamic: description-content-type
Dynamic: home-page
Dynamic: license-file
Dynamic: requires-dist
Dynamic: requires-python
Dynamic: summary
